secactpy/__init__.py
secactpy/batch.py
secactpy/cli.py
secactpy/inference.py
secactpy/io.py
secactpy/ridge.py
secactpy/rng.py
secactpy/signature.py
secactpy/data/CytoSig.tsv.gz
secactpy/data/SecAct.tsv.gz
secactpy/data/__init__.py
secactpy-0.2.0.dist-info/licenses/LICENSE
secactpy-0.2.0.dist-info/METADATA
secactpy-0.2.0.dist-info/WHEEL
secactpy-0.2.0.dist-info/entry_points.txt
secactpy-0.2.0.dist-info/top_level.txt
secactpy-0.2.0.dist-info/RECORD
