Metadata-Version: 2.4
Name: secactpy
Version: 0.2.0
Summary: Secreted Protein Activity Inference using Ridge Regression
Author: Beibei Ru, Peng Jiang
Author-email: Seongyong Park <seongyong.park@nih.gov>
Maintainer: Data2Intelligence Lab
Maintainer-email: Seongyong Park <seongyong.park@nih.gov>
License: MIT
Project-URL: Homepage, https://github.com/data2intelligence/SecActPy
Project-URL: Documentation, https://github.com/data2intelligence/SecActPy#readme
Project-URL: Repository, https://github.com/data2intelligence/SecActPy
Project-URL: Issues, https://github.com/data2intelligence/SecActPy/issues
Project-URL: Original R Package, https://github.com/data2intelligence/SecAct
Keywords: bioinformatics,single-cell,spatial-transcriptomics,cytokine,signaling,ridge-regression,secreted-proteins,cell-communication,tumor-microenvironment
Classifier: Development Status :: 4 - Beta
Classifier: Intended Audience :: Science/Research
Classifier: License :: OSI Approved :: MIT License
Classifier: Operating System :: OS Independent
Classifier: Programming Language :: Python :: 3
Classifier: Programming Language :: Python :: 3.9
Classifier: Programming Language :: Python :: 3.10
Classifier: Programming Language :: Python :: 3.11
Classifier: Programming Language :: Python :: 3.12
Classifier: Topic :: Scientific/Engineering :: Bio-Informatics
Requires-Python: >=3.9
License-File: LICENSE
Requires-Dist: numpy>=1.20.0
Requires-Dist: pandas>=1.3.0
Requires-Dist: scipy>=1.7.0
Requires-Dist: h5py>=3.0.0
Requires-Dist: anndata>=0.8.0
Requires-Dist: scanpy>=1.9.0
Provides-Extra: gpu
Requires-Dist: cupy-cuda11x>=10.0.0; extra == "gpu"
Provides-Extra: dev
Requires-Dist: pytest>=7.0.0; extra == "dev"
Requires-Dist: pytest-cov>=4.0.0; extra == "dev"
Requires-Dist: black>=23.0.0; extra == "dev"
Requires-Dist: ruff>=0.1.0; extra == "dev"
Dynamic: license-file
